README
roundy.py
setup.py
roundy.egg-info/PKG-INFO
roundy.egg-info/SOURCES.txt
roundy.egg-info/dependency_links.txt
roundy.egg-info/requires.txt
roundy.egg-info/top_level.txt