Metadata-Version: 1.0
Name: roundy
Version: 0.1a
Summary: a template language which is inspired by LISP and converts to HTML
Home-page: http://pypi.python.org/pypi/roundy
Author: Simon Liedtke
Author-email: liedtke.simon@googlemail.com
License: WTFPL
Platform: UNKNOWN
Classifier: Development Status :: 2 - Pre-Alpha
Classifier: Environment :: Console
Classifier: Intended Audience :: Developers
Classifier: Topic :: Text Processing
Classifier: Topic :: Text Processing :: Markup
